wc_csv/__init__.py
wc_csv/convert_wc_csv.py
wc_csv-0.24.dist-info/METADATA
wc_csv-0.24.dist-info/WHEEL
wc_csv-0.24.dist-info/top_level.txt
wc_csv-0.24.dist-info/RECORD
