Metadata-Version: 2.1
Name: wc-csv
Version: 0.24
Summary: This tool can be csv to string
Home-page: https://github.com/Oshita/wc_csv
Author: NoriakiOshita
Author-email: oshitanoriaki@gmail.com
License: MIT
Keywords: wordcloud csv
Platform: UNKNOWN
